topaz_agent_kit/.gitignore
topaz_agent_kit/__init__.py
topaz_agent_kit/__main__.py
topaz_agent_kit/agents/__init__.py
topaz_agent_kit/agents/agent_factory.py
topaz_agent_kit/agents/base/__init__.py
topaz_agent_kit/agents/base/adk_base_agent.py
topaz_agent_kit/agents/base/agno_base_agent.py
topaz_agent_kit/agents/base/base_agent.py
topaz_agent_kit/agents/base/crewai_base_agent.py
topaz_agent_kit/agents/base/langgraph_base_agent.py
topaz_agent_kit/agents/base/maf_base_agent.py
topaz_agent_kit/agents/base/oak_base_agent.py
topaz_agent_kit/agents/base/sk_base_agent.py
topaz_agent_kit/cli/__init__.py
topaz_agent_kit/cli/agent_generator.py
topaz_agent_kit/cli/config_validator.py
topaz_agent_kit/cli/graphviz_generator.py
topaz_agent_kit/cli/main.py
topaz_agent_kit/cli/operations_workflow_generator.py
topaz_agent_kit/cli/project_scaffolder.py
topaz_agent_kit/cli/serve_cli.py
topaz_agent_kit/cli/serve_fastapi.py
topaz_agent_kit/cli/serve_mcp.py
topaz_agent_kit/cli/serve_services.py
topaz_agent_kit/cli/service_generator.py
topaz_agent_kit/cli/stubs/__init__.py
topaz_agent_kit/cli/stubs/agents/__init__.py
topaz_agent_kit/cli/stubs/agents/universal_agent.py
topaz_agent_kit/cli/stubs/services/__init__.py
topaz_agent_kit/cli/stubs/services/remote_agent_service.py
topaz_agent_kit/core/__init__.py
topaz_agent_kit/core/ag_ui_event_emitter.py
topaz_agent_kit/core/agent_runner.py
topaz_agent_kit/core/analytics_aggregator.py
topaz_agent_kit/core/case_data_extractor.py
topaz_agent_kit/core/case_manager.py
topaz_agent_kit/core/chat_database.py
topaz_agent_kit/core/chat_storage.py
topaz_agent_kit/core/checkpoint_manager.py
topaz_agent_kit/core/configuration_engine.py
topaz_agent_kit/core/content_ingester.py
topaz_agent_kit/core/database_manager.py
topaz_agent_kit/core/exceptions.py
topaz_agent_kit/core/execution_patterns.py
topaz_agent_kit/core/file_storage.py
topaz_agent_kit/core/hitl_queue_manager.py
topaz_agent_kit/core/output_manager.py
topaz_agent_kit/core/pipeline_loader.py
topaz_agent_kit-0.10.2.dist-info/licenses/LICENSE
topaz_agent_kit-0.10.2.dist-info/METADATA
topaz_agent_kit-0.10.2.dist-info/WHEEL
topaz_agent_kit-0.10.2.dist-info/entry_points.txt
topaz_agent_kit-0.10.2.dist-info/top_level.txt
topaz_agent_kit-0.10.2.dist-info/RECORD
