Metadata-Version: 2.4
Name: topaz-agent-kit
Version: 0.10.2
Summary: Config-driven multi-agent orchestration kit with optional API/UI/MCP extras
Author: Nishant Khare
License: MIT
Keywords: nishant,topaz,agents,multi-agent,orchestration,fastapi,pipeline
Classifier: Development Status :: 3 - Alpha
Classifier: Intended Audience :: Developers
Classifier: License :: OSI Approved :: MIT License
Classifier: Programming Language :: Python :: 3
Classifier: Programming Language :: Python :: 3.11
Classifier: Programming Language :: Python :: 3.12
Classifier: Topic :: Software Development :: Libraries :: Python Modules
Requires-Python: >=3.11
License-File: LICENSE
Requires-Dist: pyyaml>=6.0.1
Requires-Dist: jsonschema>=4.21.0
Requires-Dist: fastmcp>=2.12.4
Requires-Dist: uvicorn<0.40.0,>=0.34.0
Requires-Dist: a2a-sdk>=0.1.0
Requires-Dist: langchain<2.0.0,>=1.1.0
Requires-Dist: langchain-core<2.0.0,>=1.1.0
Requires-Dist: langchain-openai<2.0.0,>=1.1.0
Requires-Dist: langchain-community<2.0.0,>=0.4.0
Requires-Dist: langchain-text-splitters<2.0.0,>=1.0.0
Requires-Dist: langchain-mcp-adapters>=0.1.9
Requires-Dist: python-dotenv>=1.0.1
Requires-Dist: jinja2>=3.1.4
Requires-Dist: pandas<3.0.0,>=2.3.1
Requires-Dist: pdfplumber>=0.11.7
Requires-Dist: pytesseract>=0.3.13
Requires-Dist: ruamel-yaml>=0.18.14
Requires-Dist: readability-lxml>=0.8.1
Requires-Dist: beautifulsoup4>=4.12.2
Requires-Dist: lxml>=4.9.3
Requires-Dist: requests<3.0.0,>=2.31.0
Requires-Dist: agno<3.0.0,>=2.2.8
Requires-Dist: langgraph<2.0.0,>=1.0.0
Requires-Dist: crewai[azure-ai-inference]<2.0.0,>=1.3.0
Requires-Dist: crewai-tools[mcp]<2.0.0,>=1.3.0
Requires-Dist: colorlog>=6.9.0
Requires-Dist: google-genai<2.0.0,>=1.32.0
Requires-Dist: rich<15.0.0,>=13.7.0
Requires-Dist: langchain-google-genai<4.0.0,>=2.1.10
Requires-Dist: ag-ui-protocol>=0.1.8
Requires-Dist: sec-api>=1.0.32
Requires-Dist: unstructured>=0.18.14
Requires-Dist: chromadb<1.2.0,>=1.1.0
Requires-Dist: onnxruntime<1.24.0,>=1.22.0
Requires-Dist: google-adk<2.0.0,>=1.15.1
Requires-Dist: pyspellchecker>=0.8.3
Requires-Dist: openai-agents[litellm]<1.0.0,>=0.2.9
Requires-Dist: docling>=2.57.0
Requires-Dist: docling-core>=2.0.0
Requires-Dist: docling-ibm-models>=2.0.0
Requires-Dist: tiktoken>=0.8.0
Requires-Dist: transformers<5.0.0,>=4.57.1
Requires-Dist: pypdf>=4.0.0
Requires-Dist: pymupdf>=1.23.0
Requires-Dist: agent-framework==1.0.0b251016
Requires-Dist: amadeus>=12.0.0
Requires-Dist: simplegmail>=4.1.1
Requires-Dist: fastapi<0.130.0,>=0.115.0
Requires-Dist: mcp>=1.13.0
Requires-Dist: semantic-kernel[mcp]<2.0.0,>=1.37.0
Requires-Dist: opentelemetry-exporter-otlp-proto-http>=1.36.0
Requires-Dist: langfuse>=3.10.6
Requires-Dist: watchdog>=3.0.0
Provides-Extra: dev
Requires-Dist: jsonschema>=4.21.0; extra == "dev"
Requires-Dist: pytest>=8.2.0; extra == "dev"
Dynamic: license-file
